ffcapcha/__init__.py
ffcapcha/antispam.py
ffcapcha/api_client.py
ffcapcha/captcha.py
ffcapcha/console.py
ffcapcha/logger.py
ffcapcha/telegram_integration.py
ffcapcha-1.3.8.dist-info/METADATA
ffcapcha-1.3.8.dist-info/WHEEL
ffcapcha-1.3.8.dist-info/entry_points.txt
ffcapcha-1.3.8.dist-info/top_level.txt
ffcapcha-1.3.8.dist-info/RECORD
