Metadata-Version: 2.4
Name: ffcapcha
Version: 1.3.8
Summary: service is aimed at protecting telegram bots from suspicious requests and DDoS attacks. Documentation about the module and resource news -> https://t.me/ffcapcha
Home-page: https://github.com/skoro_budet
Author: VndFF
Author-email: vandayzi12@gmail.com
Classifier: Development Status :: 5 - Production/Stable
Classifier: Intended Audience :: Developers
Classifier: License :: OSI Approved :: MIT License
Classifier: Operating System :: OS Independent
Classifier: Programming Language :: Python :: 3
Classifier: Programming Language :: Python :: 3.7
Classifier: Programming Language :: Python :: 3.8
Classifier: Programming Language :: Python :: 3.9
Classifier: Programming Language :: Python :: 3.10
Requires-Python: >=3.7
Requires-Dist: Pillow>=9.0.0
Requires-Dist: python-telegram-bot>=20.0
Requires-Dist: pyTelegramBotAPI>=4.0.0
Requires-Dist: requests>=2.28.0
Requires-Dist: aiogram>=3.0.0
Dynamic: author
Dynamic: author-email
Dynamic: classifier
Dynamic: description
Dynamic: description-content-type
Dynamic: home-page
Dynamic: requires-dist
Dynamic: requires-python
Dynamic: summary
